moduleInterface/__init__.py
moduleInterface/actuator.py
moduleInterface/defines.py
moduleInterface/interface.py
moduleInterface-2.1.3.dist-info/METADATA
moduleInterface-2.1.3.dist-info/WHEEL
moduleInterface-2.1.3.dist-info/top_level.txt
moduleInterface-2.1.3.dist-info/RECORD
